bdns/fetch/__init__.py
bdns/fetch/__main__.py
bdns/fetch/cli.py
bdns/fetch/client.py
bdns/fetch/endpoints.py
bdns/fetch/exceptions.py
bdns/fetch/options.py
bdns/fetch/pagination.py
bdns/fetch/types.py
bdns/fetch/utils.py
bdns_fetch-3.1.7.dist-info/METADATA
bdns_fetch-3.1.7.dist-info/WHEEL
bdns_fetch-3.1.7.dist-info/entry_points.txt
bdns_fetch-3.1.7.dist-info/licenses/LICENSE
bdns_fetch-3.1.7.dist-info/RECORD
