Metadata-Version: 2.4
Name: bdns-fetch
Version: 3.1.7
Summary: Python client and CLI to fetch data from the Base de Datos Nacional de Subvenciones (BDNS)
License: GPL-3.0
License-File: LICENSE
Keywords: bdns,subsidies,spanish-government,api,data,cli
Author: José María Cruz Lorite
Author-email: josemariacruzlorite@gmail.com
Requires-Python: >=3.11,<4.0
Classifier: Development Status :: 4 - Beta
Classifier: Environment :: Console
Classifier: Intended Audience :: Developers
Classifier: Intended Audience :: Science/Research
Classifier: License :: OSI Approved :: GNU General Public License v3 (GPLv3)
Classifier: Operating System :: OS Independent
Classifier: Programming Language :: Python :: 3
Classifier: Programming Language :: Python :: 3.11
Classifier: Programming Language :: Python :: 3.12
Classifier: Programming Language :: Python :: 3.13
Classifier: Programming Language :: Python :: 3.14
Classifier: Topic :: Scientific/Engineering :: Information Analysis
Classifier: Topic :: Software Development :: Libraries :: Python Modules
Classifier: Topic :: Utilities
Requires-Dist: aiohttp (>=3.12.15,<4.0.0)
Requires-Dist: dateparser (>=1.2.2,<2.0.0)
Requires-Dist: requests (>=2.32.5,<3.0.0)
Requires-Dist: tenacity (>=9.1.2,<10.0.0)
Requires-Dist: tqdm (>=4.67.1,<5.0.0)
Requires-Dist: typer[all] (>=0.17.4,<0.18.0)
Project-URL: Documentation, https://github.com/cruzlorite/bdns-fetch#readme
Project-URL: Homepage, https://github.com/cruzlorite/bdns-fetch
Project-URL: Repository, https://github.com/cruzlorite/bdns-fetch
